Metadata-Version: 1.0
Name: rajat-distribution
Version: 0.1
Summary: distributions
Home-page: UNKNOWN
Author: UNKNOWN
Author-email: UNKNOWN
License: UNKNOWN
Platform: UNKNOWN
